{
  "collectionName": "components_widget_contact_couples",
  "info": {
    "displayName": "ContactCouple",
    "icon": "heart",
    "description": ""
  },
  "options": {},
  "attributes": {
    "name": {
      "type": "string",
      "required": true
    },
    "description": {
      "type": "string"
    },
    "phone1": {
      "type": "string"
    },
    "phone2": {
      "type": "string"
    },
    "email1": {
      "type": "email"
    },
    "email2": {
      "type": "email"
    },
    "image": {
      "type": "media",
      "multiple": false,
      "required": false,
      "allowedTypes": [
        "images"
      ]
    }
  }
}
